LICENSE
MANIFEST.in
README.rst
setup.py
cmsplugin_price/__init__.py
cmsplugin_price/admin.py
cmsplugin_price/cms_plugins.py
cmsplugin_price/forms.py
cmsplugin_price/models.py
cmsplugin_price/settings.py
cmsplugin_price/utils.py
cmsplugin_price.egg-info/PKG-INFO
cmsplugin_price.egg-info/SOURCES.txt
cmsplugin_price.egg-info/dependency_links.txt
cmsplugin_price.egg-info/not-zip-safe
cmsplugin_price.egg-info/top_level.txt
cmsplugin_price/nospam/__init__.py
cmsplugin_price/nospam/fields.py
cmsplugin_price/nospam/forms.py
cmsplugin_price/nospam/utils.py
cmsplugin_price/nospam/widgets.py
cmsplugin_price/templates/cmsplugin_price/contact.html
cmsplugin_price/templates/cmsplugin_price/email.txt
cmsplugin_price/templates/cmsplugin_price/subject.txt
cmsplugin_price/templates/cmsplugin_price/admin/plugin_change_form.html