Metadata-Version: 1.1
Name: cmsplugin-price
Version: 1.0.5
Summary: Extendable price form plugin for Django CMS with spam protection and i18n
Home-page: http://github.com/vinitkumar/cmsplugin-price
Author: Vinit Kumar
Author-email: vinit.kumar@changer.nl.com
License: UNKNOWN
Keywords: price form django cms django-cms spam protection email
Platform: UNKNOWN
Classifier: Development Status :: 5 - Production/Stable
Classifier: Environment :: Web Environment
Classifier: Intended Audience :: Developers
Classifier: License :: OSI Approved :: BSD License
Classifier: Operating System :: OS Independent
Classifier: Programming Language :: Python
Classifier: Framework :: Django
